{
  "type": "FeatureCollection",
  "name": "M20_waypoints_sol1108_all",
  "features": [
    {
      "type": "Feature",
      "properties": {
        "RMC": "51_2390",
        "site": 51,
        "drive": 2390,
        "sol": 1108,
        "easting": 4347364.412,
        "northing": 1096024.588,
        "elev_geoid": -2369.986084,
        "elev_radii": -4058.368164,
        "radius": 3392131.632,
        "lon": 77.32407431,
        "lat": 18.49059774,
        "roll": 4.2949469,
        "pitch": 1.253548412,
        "yaw": -92.22775216,
        "yaw_rad": -1.609677937,
        "tilt": 4.473813588,
        "dist_m": 56.333,
        "dist_total_m": 25222.594,
        "dist_km": 25.22,
        "dist_mi": 15.67,
        "final": "y",
        "Note": "Used Mobility Report WID 41081",
        "images": [
          {
            "name": "Panorama",
            "isPanoramic": true,
            "url": "Layers/mosaics/N_LRGB_1108_RZS_0512390_CYL_L_AUTOGENJ01.jpg",
            "rows": "4170",
            "columns": "15399",
            "azmin": "76.0528",
            "azmax": "14.3601",
            "elmin": "-66.5311",
            "elmax": "14.2466",
            "elzero": "736.459"
          }
        ]
      },
      "geometry": {
        "type": "Point",
        "coordinates": [
          77.32407431,
          18.49059774,
          -2369.986084
        ]
      }
    }
  ]
}
