{
  "type": "FeatureCollection",
  "name": "M20_waypoints_sol543_all",
  "features": [
    {
      "type": "Feature",
      "properties": {
        "RMC": "26_5150",
        "site": 26,
        "drive": 5150,
        "sol": 543,
        "easting": 4351909.269,
        "northing": 1093634.489,
        "elev_geoid": -2541.163818,
        "elev_radii": -4224.961426,
        "radius": 3391965.04,
        "lon": 77.40491107,
        "lat": 18.45027532,
        "roll": 3.191794,
        "pitch": 4.037246,
        "yaw": -119.591011,
        "yaw_rad": -2.0873,
        "tilt": 5.144904,
        "dist_m": 142.964,
        "dist_total_m": 12562.289,
        "dist_km": 12.56,
        "dist_mi": 7.81,
        "final": "y",
        "Note": "Used Mobility Report WID 55431"
      },
      "geometry": {
        "type": "Point",
        "coordinates": [
          77.40491107,
          18.45027532,
          -2541.163818
        ]
      }
    }
  ]
}
