{
  "type": "FeatureCollection",
  "name": "M20_waypoints_current",
  "features": [
    {
      "type": "Feature",
      "properties": {
        "RMC": "8_734",
        "site": 8,
        "drive": 734,
        "sol": 285,
        "easting": 4353963.479,
        "northing": 1092596.904,
        "elev_geoid": -2574.898438,
        "elev_radii": -4256.230469,
        "radius": 3391933.77,
        "lon": 77.44144812,
        "lat": 18.43277064,
        "roll": -1.585839,
        "pitch": 3.233621,
        "yaw": -130.337289,
        "yaw_rad": -2.2748,
        "tilt": 3.601183,
        "dist_m": 62.35015534,
        "dist_total": 2817.38,
        "dist_km": 2.82,
        "dist_mi": 1.75,
        "final": "y",
        "Note": "Used Mobility Report WID 32853"
      },
      "geometry": {
        "type": "Point",
        "coordinates": [
          77.44144812000008,
          18.432770640000058,
          -2574.8984000000055
        ]
      }
    }
  ]
}
