{
  "type": "FeatureCollection",
  "name": "M20_waypoints_current",
  "features": [
    {
      "type": "Feature",
      "properties": {
        "RMC": "7_2050",
        "site": 7,
        "drive": 2050,
        "sol": 210,
        "easting": 4354001.307,
        "northing": 1092657.036,
        "elev_geoid": -2573.32,
        "elev_radii": -4254.74,
        "radius": 3391935.26,
        "lon": 77.44212095,
        "lat": 18.4337851,
        "roll": -5.25622,
        "pitch": 4.527471,
        "yaw": 27.65755,
        "yaw_rad": 0.48,
        "tilt": 6.93313,
        "dist_m": 53.352832,
        "dist_total": 2609.43,
        "dist_km": 2.61,
        "dist_mi": 1.62,
        "final": "y",
        "Note": "Used Mobility Report WID 32101"
      },
      "geometry": {
        "type": "Point",
        "coordinates": [
          77.44212095000006,
          18.433785100000023,
          -2573.320000000007
        ]
      }
    }
  ]
}
